Metadata-Version: 2.1
Name: hello-world-programm
Version: 0.0.1
Summary: a hello world description example
Author: Gaurav Chaudhary
Classifier: Programming Language :: Python :: 3
Classifier: License :: OSI Approved :: MIT License
Classifier: Operating System :: OS Independent
